cloud_harvester/__init__.py
cloud_harvester/api.py
cloud_harvester/application/__init__.py
cloud_harvester/application/collect_resources.py
cloud_harvester/domain/__init__.py
cloud_harvester/domain/enums.py
cloud_harvester/domain/models.py
cloud_harvester/infrastructure/__init__.py
cloud_harvester/infrastructure/providers/__init__.py
cloud_harvester/infrastructure/providers/aws/__init__.py
cloud_harvester/infrastructure/providers/aws/auth.py
cloud_harvester/infrastructure/providers/aws/compute.py
cloud_harvester/infrastructure/providers/aws/containers.py
cloud_harvester/infrastructure/providers/aws/databases.py
cloud_harvester/infrastructure/providers/aws/networking.py
cloud_harvester/infrastructure/providers/aws/observability.py
cloud_harvester/infrastructure/providers/aws/security.py
cloud_harvester/infrastructure/providers/aws/serverless.py
cloud_harvester/infrastructure/providers/aws/storage.py
cloud_harvester/infrastructure/providers/aws/utils.py
cloud_harvester/infrastructure/providers/azure/__init__.py
cloud_harvester/infrastructure/providers/azure/clients.py
cloud_harvester/infrastructure/providers/azure/compute.py
cloud_harvester/infrastructure/providers/azure/databases.py
cloud_harvester/infrastructure/providers/azure/monitoring.py
cloud_harvester/infrastructure/providers/azure/networking.py
cloud_harvester/infrastructure/providers/azure/resource_graph.py
cloud_harvester/infrastructure/providers/azure/security.py
cloud_harvester/infrastructure/providers/azure/storage.py
cloud_harvester/infrastructure/providers/azure/utils.py
cloud_harvester-0.1.2.dist-info/licenses/LICENSE
cloud_harvester-0.1.2.dist-info/METADATA
cloud_harvester-0.1.2.dist-info/WHEEL
cloud_harvester-0.1.2.dist-info/top_level.txt
cloud_harvester-0.1.2.dist-info/RECORD
