Metadata-Version: 2.4
Name: cloud-harvester
Version: 0.1.2
Summary: Cloud-agnostic resource harvesting with a unified resource model.
Author-email: Marco <marco1088@hotmail.nl>
License: Proprietary
Project-URL: Homepage, https://github.com/mrcotrmpr/cloud-harvester
Project-URL: Repository, https://github.com/mrcotrmpr/cloud-harvester
Project-URL: Issues, https://github.com/mrcotrmpr/cloud-harvester/issues
Keywords: cloud,aws,azure,inventory,resources,harvester
Classifier: Development Status :: 3 - Alpha
Classifier: Intended Audience :: Information Technology
Classifier: License :: Other/Proprietary License
Classifier: Operating System :: OS Independent
Classifier: Programming Language :: Python :: 3
Classifier: Programming Language :: Python :: 3.12
Classifier: Topic :: System :: Monitoring
Requires-Python: >=3.12
License-File: LICENSE
Requires-Dist: boto3<2,>=1.28
Requires-Dist: azure-identity<2,>=1.15
Requires-Dist: azure-mgmt-compute<31,>=30
Requires-Dist: azure-mgmt-network<26,>=25
Requires-Dist: botocore>=1.41.5
Requires-Dist: boto3-stubs>=1.41.5
Requires-Dist: azure-mgmt-containerinstance>=10.1.0
Requires-Dist: azure-mgmt-containerservice>=40.2.0
Requires-Dist: azure-mgmt-storage>=24.0.0
Requires-Dist: azure-storage-blob>=12.27.1
Requires-Dist: azure-storage-file-share>=12.23.1
Requires-Dist: azure-mgmt-sql>=3.0.1
Requires-Dist: azure-mgmt-rdbms>=10.1.1
Requires-Dist: azure-cosmos>=4.14.2
Requires-Dist: azure-mgmt-redis>=14.5.0
Requires-Dist: azure-mgmt-synapse>=2.0.0
Requires-Dist: azure-mgmt-dns>=9.0.0
Requires-Dist: azure-mgmt-apimanagement>=5.0.0
Requires-Dist: azure-mgmt-frontdoor>=1.2.0
Requires-Dist: azure-mgmt-cdn>=13.1.1
Requires-Dist: azure-mgmt-security>=7.0.0
Requires-Dist: azure-graphrbac>=0.61.2
Requires-Dist: azure-mgmt-monitor>=7.0.0
Requires-Dist: azure-mgmt-resource>=24.0.0
Requires-Dist: azure-mgmt-resourcegraph>=8.0.1
Requires-Dist: azure-mgmt-recoveryservices>=4.0.0
Requires-Dist: azure-mgmt-recoveryservicesbackup>=10.0.0
Requires-Dist: azure-mgmt-automation>=1.0.0
Dynamic: license-file
